ProsNet/__init__.py
ProsNet/helper.py
ProsNet/plotter.py
ProsNet/activity_monitor/__init__.py
ProsNet/activity_monitor/activity_monitor_abc.py
ProsNet/activity_monitor/activpal.py
ProsNet/dataset/__init__.py
ProsNet/dataset/dataset.py
ProsNet/dataset/dataset_abc.py
ProsNet/dataset/engineering_set.py
ProsNet/dataset/feature_set.py
ProsNet/model/__init__.py
ProsNet/model/deep_model.py
ProsNet/model/model.py
ProsNet/model/model_abc.py
ProsNet/model/shallow_model.py
ProsNet/stack/__init__.py
ProsNet/stack/epoch_stack.py
ProsNet/stack/non_wear_stack.py
ProsNet/stack/posture_stack_abc.py
ProsNet-0.0.5.dist-info/LICENCE
ProsNet-0.0.5.dist-info/METADATA
ProsNet-0.0.5.dist-info/WHEEL
ProsNet-0.0.5.dist-info/top_level.txt
ProsNet-0.0.5.dist-info/RECORD
