Metadata-Version: 2.1
Name: ProsNet
Version: 0.0.5
Summary: A package for processing activPAL activity monitor data.
Home-page: https://github.com/Ben-Jamin-Griff/ProsNet
Author: Benjamin Griffiths
License: UNKNOWN
Project-URL: Bug Tracker, https://github.com/Ben-Jamin-Griff/ProsNet/issues
Platform: UNKNOWN
Classifier: Programming Language :: Python :: 3
Classifier: License :: OSI Approved :: MIT License
Classifier: Operating System :: OS Independent
Requires-Python: >=3.6
License-File: LICENCE
Requires-Dist: requests
Requires-Dist: pandas
Requires-Dist: matplotlib
Requires-Dist: scipy
Requires-Dist: uos-activpal
Requires-Dist: numba
Requires-Dist: seaborn
Requires-Dist: sklearn
Requires-Dist: numpy (==1.20)
